autoclip/__init__.py
autoclip/tf/__init__.py
autoclip/tf/quantile.py
autoclip/torch/__init__.py
autoclip/torch/clipper.py
autoclip/torch/quantile.py
autoclip/torch/std.py
autoclip/torch/utils.py
autoclip-0.2.1.dist-info/LICENSE
autoclip-0.2.1.dist-info/METADATA
autoclip-0.2.1.dist-info/WHEEL
autoclip-0.2.1.dist-info/top_level.txt
autoclip-0.2.1.dist-info/RECORD
