Metadata-Version: 2.1
Name: autoclip
Version: 0.2.1
Summary: Smart gradient clippers
Home-page: https://github.com/HesitantlyHuman/autoclip
Author: HesitantlyHuman
Author-email: tannersims@hesitantlyhuman.com
License: MIT
License-File: LICENSE
